{
  "scan_date": "2026-06-28T21:02:07.331872+00:00",
  "scan_date_human": "2026-06-28 23:02",
  "total": 43,
  "results": [
    {
      "ticker": "XLK",
      "name": "Tecnolog\u00eda",
      "group": "Sectorial",
      "current_price": 181.11000061035156,
      "drawdown_from_ath_pct": -5.074890165196471,
      "fiftytwo_week_change": 38.586024339022934,
      "monthly_signal": null,
      "monthly_wt2": 62.56604665663868,
      "weekly_entry": null,
      "weekly_exit": null,
      "weekly_mfi": 21.564218208545224,
      "ash_bullish": true
    },
    {
      "ticker": "XLF",
      "name": "Financiero",
      "group": "Sectorial",
      "current_price": 53.56999969482422,
      "drawdown_from_ath_pct": -0.9990157043170692,
      "fiftytwo_week_change": 3.8788231520691947,
      "monthly_signal": null,
      "monthly_wt2": 39.11723410354718,
      "weekly_entry": null,
      "weekly_exit": null,
      "weekly_mfi": 13.530414314688734,
      "ash_bullish": false
    },
    {
      "ticker": "XLE",
      "name": "Energ\u00eda",
      "group": "Sectorial",
      "current_price": 53.84000015258789,
      "drawdown_from_ath_pct": -10.900106436302986,
      "fiftytwo_week_change": 27.31941204690072,
      "monthly_signal": {
        "type": "SELL",
        "wt2": 65.92046825176952,
        "bars_ago": 0
      },
      "monthly_wt2": 65.92046825176952,
      "weekly_entry": null,
      "weekly_exit": null,
      "weekly_mfi": 13.441510286161625,
      "ash_bullish": false
    },
    {
      "ticker": "XLV",
      "name": "Salud",
      "group": "Sectorial",
      "current_price": 160.33999633789062,
      "drawdown_from_ath_pct": 0.0,
      "fiftytwo_week_change": 25.078971556907963,
      "monthly_signal": null,
      "monthly_wt2": 33.0006916802653,
      "weekly_entry": null,
      "weekly_exit": null,
      "weekly_mfi": 11.466420930523109,
      "ash_bullish": false
    },
    {
      "ticker": "XLI",
      "name": "Industrial",
      "group": "Sectorial",
      "current_price": 181.1999969482422,
      "drawdown_from_ath_pct": 0.0,
      "fiftytwo_week_change": 20.738930871145495,
      "monthly_signal": null,
      "monthly_wt2": 70.26049268168524,
      "weekly_entry": null,
      "weekly_exit": null,
      "weekly_mfi": 19.05419270329558,
      "ash_bullish": true
    },
    {
      "ticker": "XLY",
      "name": "Consumo discrecional",
      "group": "Sectorial",
      "current_price": 114.37000274658203,
      "drawdown_from_ath_pct": -5.233872309565075,
      "fiftytwo_week_change": 4.1038748084429475,
      "monthly_signal": null,
      "monthly_wt2": 43.14613862508072,
      "weekly_entry": null,
      "weekly_exit": null,
      "weekly_mfi": 8.266398247598735,
      "ash_bullish": false
    },
    {
      "ticker": "XLP",
      "name": "Consumo b\u00e1sico",
      "group": "Sectorial",
      "current_price": 84.70999908447266,
      "drawdown_from_ath_pct": -4.7018281396783,
      "fiftytwo_week_change": 9.124327881625986,
      "monthly_signal": null,
      "monthly_wt2": 52.16996965438557,
      "weekly_entry": null,
      "weekly_exit": null,
      "weekly_mfi": 9.820406502632997,
      "ash_bullish": false
    },
    {
      "ticker": "XLU",
      "name": "Utilities",
      "group": "Sectorial",
      "current_price": 46.20000076293945,
      "drawdown_from_ath_pct": -1.9063980059004935,
      "fiftytwo_week_change": 10.863454188402237,
      "monthly_signal": {
        "type": "SELL",
        "wt2": 61.34448364479712,
        "bars_ago": 1
      },
      "monthly_wt2": 60.44884225072718,
      "weekly_entry": null,
      "weekly_exit": null,
      "weekly_mfi": 11.974518579779572,
      "ash_bullish": false
    },
    {
      "ticker": "XLB",
      "name": "Materiales",
      "group": "Sectorial",
      "current_price": 51.599998474121094,
      "drawdown_from_ath_pct": -2.5963916689877498,
      "fiftytwo_week_change": 19.77650316893536,
      "monthly_signal": null,
      "monthly_wt2": 53.08098930029391,
      "weekly_entry": null,
      "weekly_exit": null,
      "weekly_mfi": 15.682877400842598,
      "ash_bullish": false
    },
    {
      "ticker": "XLRE",
      "name": "Inmobiliario",
      "group": "Sectorial",
      "current_price": 45.2400016784668,
      "drawdown_from_ath_pct": 0.0,
      "fiftytwo_week_change": 13.015644698042719,
      "monthly_signal": null,
      "monthly_wt2": 54.60749997636079,
      "weekly_entry": null,
      "weekly_exit": null,
      "weekly_mfi": 11.045191246322991,
      "ash_bullish": false
    },
    {
      "ticker": "XLC",
      "name": "Comunicaciones",
      "group": "Sectorial",
      "current_price": 106.18000030517578,
      "drawdown_from_ath_pct": -11.06267363251246,
      "fiftytwo_week_change": 0.09807539621604178,
      "monthly_signal": null,
      "monthly_wt2": 53.325724470562214,
      "weekly_entry": null,
      "weekly_exit": null,
      "weekly_mfi": 10.929480004871436,
      "ash_bullish": false
    },
    {
      "ticker": "SPY",
      "name": "S&P 500",
      "group": "\u00cdndice",
      "current_price": 728.989990234375,
      "drawdown_from_ath_pct": -3.3856751807104164,
      "fiftytwo_week_change": 16.60982675240998,
      "monthly_signal": null,
      "monthly_wt2": 64.6327882267657,
      "weekly_entry": null,
      "weekly_exit": null,
      "weekly_mfi": 22.521691301567838,
      "ash_bullish": false
    },
    {
      "ticker": "QQQ",
      "name": "Nasdaq 100",
      "group": "\u00cdndice",
      "current_price": 706.52001953125,
      "drawdown_from_ath_pct": -4.200611891294949,
      "fiftytwo_week_change": 25.647827527775902,
      "monthly_signal": null,
      "monthly_wt2": 64.44414590967843,
      "weekly_entry": null,
      "weekly_exit": null,
      "weekly_mfi": 21.510058593491056,
      "ash_bullish": true
    },
    {
      "ticker": "IWM",
      "name": "Russell 2000",
      "group": "\u00cdndice",
      "current_price": 299.8299865722656,
      "drawdown_from_ath_pct": 0.0,
      "fiftytwo_week_change": 38.08475431343171,
      "monthly_signal": null,
      "monthly_wt2": 61.628808054612286,
      "weekly_entry": null,
      "weekly_exit": null,
      "weekly_mfi": 13.67283270569969,
      "ash_bullish": true
    },
    {
      "ticker": "ARKK",
      "name": "Innovaci\u00f3n",
      "group": "ARK",
      "current_price": 78.12999725341797,
      "drawdown_from_ath_pct": -42.20607971213245,
      "fiftytwo_week_change": 3.716972460246227,
      "monthly_signal": null,
      "monthly_wt2": 41.25136943886622,
      "weekly_entry": null,
      "weekly_exit": null,
      "weekly_mfi": 10.830938842511152,
      "ash_bullish": false
    },
    {
      "ticker": "ARKG",
      "name": "Gen\u00f3mica",
      "group": "ARK",
      "current_price": 41.43000030517578,
      "drawdown_from_ath_pct": -59.09815192300291,
      "fiftytwo_week_change": 73.92947454226034,
      "monthly_signal": null,
      "monthly_wt2": 25.130441799532935,
      "weekly_entry": null,
      "weekly_exit": null,
      "weekly_mfi": 6.821559907842989,
      "ash_bullish": true
    },
    {
      "ticker": "ARKW",
      "name": "Internet / Web",
      "group": "ARK",
      "current_price": 139.22000122070312,
      "drawdown_from_ath_pct": -20.083410368889513,
      "fiftytwo_week_change": -10.50678370067814,
      "monthly_signal": null,
      "monthly_wt2": 37.43471120138741,
      "weekly_entry": null,
      "weekly_exit": null,
      "weekly_mfi": 14.51326195292851,
      "ash_bullish": false
    },
    {
      "ticker": "ARKF",
      "name": "Fintech",
      "group": "ARK",
      "current_price": 39.20000076293945,
      "drawdown_from_ath_pct": -30.925568458370435,
      "fiftytwo_week_change": -26.92442122382569,
      "monthly_signal": null,
      "monthly_wt2": 21.84116670193366,
      "weekly_entry": null,
      "weekly_exit": null,
      "weekly_mfi": 5.232906569383914,
      "ash_bullish": false
    },
    {
      "ticker": "ARKQ",
      "name": "Automatizaci\u00f3n/Rob\u00f3tica",
      "group": "ARK",
      "current_price": 123.5999984741211,
      "drawdown_from_ath_pct": -13.487784210575782,
      "fiftytwo_week_change": 27.657732424081054,
      "monthly_signal": {
        "type": "SELL_PLUS",
        "wt2": 71.46286530888854,
        "bars_ago": 0
      },
      "monthly_wt2": 71.46286530888854,
      "weekly_entry": null,
      "weekly_exit": null,
      "weekly_mfi": 14.406690691872504,
      "ash_bullish": false
    },
    {
      "ticker": "ARKX",
      "name": "Espacio (ARK)",
      "group": "ARK",
      "current_price": 31.93000030517578,
      "drawdown_from_ath_pct": -14.579990923510833,
      "fiftytwo_week_change": 22.290308536097175,
      "monthly_signal": {
        "type": "SELL_PLUS",
        "wt2": 73.78730775197513,
        "bars_ago": 0
      },
      "monthly_wt2": 73.78730775197513,
      "weekly_entry": null,
      "weekly_exit": null,
      "weekly_mfi": 5.982550090691816,
      "ash_bullish": false
    },
    {
      "ticker": "UFO",
      "name": "Espacio global",
      "group": "Espacio",
      "current_price": 46.189998626708984,
      "drawdown_from_ath_pct": -29.2757612105727,
      "fiftytwo_week_change": 56.092663248512,
      "monthly_signal": {
        "type": "SELL",
        "wt2": 76.5696916378941,
        "bars_ago": 0
      },
      "monthly_wt2": 76.5696916378941,
      "weekly_entry": null,
      "weekly_exit": "WT_SELL_PLUS",
      "weekly_mfi": 18.90305054740096,
      "ash_bullish": false
    },
    {
      "ticker": "MSOS",
      "name": "Cannabis US",
      "group": "Cannabis",
      "current_price": 4.690000057220459,
      "drawdown_from_ath_pct": -90.1787314087102,
      "fiftytwo_week_change": 65.72438811512838,
      "monthly_signal": {
        "type": "BUY",
        "wt2": -18.702981984786135,
        "bars_ago": 2
      },
      "monthly_wt2": -9.10685702068917,
      "weekly_entry": null,
      "weekly_exit": null,
      "weekly_mfi": -6.0781830851664695,
      "ash_bullish": false
    },
    {
      "ticker": "MJ",
      "name": "Cannabis global",
      "group": "Cannabis",
      "current_price": 24.43000030517578,
      "drawdown_from_ath_pct": -93.08772439878258,
      "fiftytwo_week_change": 19.88601784874227,
      "monthly_signal": {
        "type": "BUY",
        "wt2": -19.16659623251464,
        "bars_ago": 2
      },
      "monthly_wt2": -19.75247089259226,
      "weekly_entry": null,
      "weekly_exit": null,
      "weekly_mfi": -8.552714259484256,
      "ash_bullish": false
    },
    {
      "ticker": "SMH",
      "name": "Semiconductores",
      "group": "Tecnolog\u00eda",
      "current_price": 611.6099853515625,
      "drawdown_from_ath_pct": 0.0,
      "fiftytwo_week_change": 112.44998881632159,
      "monthly_signal": {
        "type": "SELL",
        "wt2": 70.03596200285428,
        "bars_ago": 3
      },
      "monthly_wt2": 78.49296169668004,
      "weekly_entry": null,
      "weekly_exit": "WT_SELL_PLUS",
      "weekly_mfi": 28.737523699557496,
      "ash_bullish": true
    },
    {
      "ticker": "BOTZ",
      "name": "Rob\u00f3tica e IA",
      "group": "Tecnolog\u00eda",
      "current_price": 36.0099983215332,
      "drawdown_from_ath_pct": -10.311340092172204,
      "fiftytwo_week_change": 8.05343215237497,
      "monthly_signal": null,
      "monthly_wt2": 51.1288047868295,
      "weekly_entry": null,
      "weekly_exit": null,
      "weekly_mfi": 9.269984840192384,
      "ash_bullish": false
    },
    {
      "ticker": "DRIV",
      "name": "Coches el\u00e9ctricos/auton.",
      "group": "Tecnolog\u00eda",
      "current_price": 37.05059814453125,
      "drawdown_from_ath_pct": -10.927498926554698,
      "fiftytwo_week_change": 55.062158781667605,
      "monthly_signal": null,
      "monthly_wt2": 60.669360907321845,
      "weekly_entry": null,
      "weekly_exit": "WT_SELL_PLUS",
      "weekly_mfi": 27.254793044275925,
      "ash_bullish": false
    },
    {
      "ticker": "HACK",
      "name": "Ciberseguridad",
      "group": "Tecnolog\u00eda",
      "current_price": 98.6500015258789,
      "drawdown_from_ath_pct": -0.7045767075925263,
      "fiftytwo_week_change": 16.294909485566535,
      "monthly_signal": null,
      "monthly_wt2": 34.870539009407615,
      "weekly_entry": null,
      "weekly_exit": null,
      "weekly_mfi": 17.437053276596313,
      "ash_bullish": true
    },
    {
      "ticker": "CIBR",
      "name": "Ciberseguridad (2)",
      "group": "Tecnolog\u00eda",
      "current_price": 85.36000061035156,
      "drawdown_from_ath_pct": -4.050537947197337,
      "fiftytwo_week_change": 18.061227655455518,
      "monthly_signal": null,
      "monthly_wt2": 34.43633128762585,
      "weekly_entry": null,
      "weekly_exit": null,
      "weekly_mfi": 11.776266038998186,
      "ash_bullish": true
    },
    {
      "ticker": "FINX",
      "name": "Fintech",
      "group": "Tecnolog\u00eda",
      "current_price": 24.899999618530273,
      "drawdown_from_ath_pct": -48.03742405987085,
      "fiftytwo_week_change": -27.012244267215795,
      "monthly_signal": null,
      "monthly_wt2": -10.103441824755768,
      "weekly_entry": null,
      "weekly_exit": null,
      "weekly_mfi": 6.44506870175341,
      "ash_bullish": false
    },
    {
      "ticker": "BLOK",
      "name": "Blockchain",
      "group": "Tecnolog\u00eda",
      "current_price": 63.16999816894531,
      "drawdown_from_ath_pct": -8.140658381910946,
      "fiftytwo_week_change": 7.708424284776926,
      "monthly_signal": null,
      "monthly_wt2": 46.20428964698913,
      "weekly_entry": null,
      "weekly_exit": null,
      "weekly_mfi": 10.411951687792769,
      "ash_bullish": false
    },
    {
      "ticker": "ICLN",
      "name": "Energ\u00eda limpia",
      "group": "Energ\u00eda limpia",
      "current_price": 19.5,
      "drawdown_from_ath_pct": -44.267843627488496,
      "fiftytwo_week_change": 46.93855728339726,
      "monthly_signal": null,
      "monthly_wt2": 43.26038038227486,
      "weekly_entry": null,
      "weekly_exit": "WT_SELL_PLUS",
      "weekly_mfi": 20.161799443883684,
      "ash_bullish": false
    },
    {
      "ticker": "TAN",
      "name": "Solar",
      "group": "Energ\u00eda limpia",
      "current_price": 56.849998474121094,
      "drawdown_from_ath_pct": -72.30455447958629,
      "fiftytwo_week_change": 54.48369470852757,
      "monthly_signal": null,
      "monthly_wt2": 33.607088350811026,
      "weekly_entry": null,
      "weekly_exit": "WT_SELL_PLUS",
      "weekly_mfi": 15.183914768604263,
      "ash_bullish": false
    },
    {
      "ticker": "LIT",
      "name": "Litio y bater\u00edas",
      "group": "Energ\u00eda limpia",
      "current_price": 75.93000030517578,
      "drawdown_from_ath_pct": -15.22747481410354,
      "fiftytwo_week_change": 85.78863868800397,
      "monthly_signal": null,
      "monthly_wt2": 46.09666264093325,
      "weekly_entry": null,
      "weekly_exit": null,
      "weekly_mfi": 23.031640144926353,
      "ash_bullish": false
    },
    {
      "ticker": "URA",
      "name": "Uranio",
      "group": "Energ\u00eda limpia",
      "current_price": 43.59000015258789,
      "drawdown_from_ath_pct": -47.23391327653285,
      "fiftytwo_week_change": 16.03366247012936,
      "monthly_signal": {
        "type": "SELL",
        "wt2": 62.22801168869544,
        "bars_ago": 3
      },
      "monthly_wt2": 58.841613113336585,
      "weekly_entry": null,
      "weekly_exit": null,
      "weekly_mfi": 12.799063632293452,
      "ash_bullish": false
    },
    {
      "ticker": "IBIT",
      "name": "Bitcoin (iShares)",
      "group": "Cripto",
      "current_price": 33.849998474121094,
      "drawdown_from_ath_pct": -48.95959193322669,
      "fiftytwo_week_change": -48.95959193322669,
      "monthly_signal": null,
      "monthly_wt2": 31.32940303043559,
      "weekly_entry": null,
      "weekly_exit": null,
      "weekly_mfi": -6.75402049042615,
      "ash_bullish": false
    },
    {
      "ticker": "GBTC",
      "name": "Bitcoin (Grayscale)",
      "group": "Cripto",
      "current_price": 46.279998779296875,
      "drawdown_from_ath_pct": -49.575071480893925,
      "fiftytwo_week_change": -49.575071480893925,
      "monthly_signal": null,
      "monthly_wt2": 1.707707659242739,
      "weekly_entry": null,
      "weekly_exit": null,
      "weekly_mfi": -7.736280705632379,
      "ash_bullish": false
    },
    {
      "ticker": "GDX",
      "name": "Mineras de oro",
      "group": "Materias primas",
      "current_price": 77.0,
      "drawdown_from_ath_pct": -33.52900342348015,
      "fiftytwo_week_change": 50.19216477269852,
      "monthly_signal": {
        "type": "SELL",
        "wt2": 88.03926624399986,
        "bars_ago": 3
      },
      "monthly_wt2": 76.19753391324643,
      "weekly_entry": null,
      "weekly_exit": null,
      "weekly_mfi": 21.498570704261997,
      "ash_bullish": false
    },
    {
      "ticker": "REMX",
      "name": "Tierras raras",
      "group": "Materias primas",
      "current_price": 86.52999877929688,
      "drawdown_from_ath_pct": -59.20425848081917,
      "fiftytwo_week_change": 79.01129831591437,
      "monthly_signal": null,
      "monthly_wt2": 43.37070054920338,
      "weekly_entry": null,
      "weekly_exit": null,
      "weekly_mfi": 17.772804696477817,
      "ash_bullish": false
    },
    {
      "ticker": "XBI",
      "name": "Biotech (small)",
      "group": "Biotech",
      "current_price": 155.3800048828125,
      "drawdown_from_ath_pct": 0.0,
      "fiftytwo_week_change": 82.22174701773145,
      "monthly_signal": null,
      "monthly_wt2": 50.52184734623983,
      "weekly_entry": null,
      "weekly_exit": null,
      "weekly_mfi": 17.66804739838764,
      "ash_bullish": true
    },
    {
      "ticker": "IBB",
      "name": "Biotech (large)",
      "group": "Biotech",
      "current_price": 187.36000061035156,
      "drawdown_from_ath_pct": 0.0,
      "fiftytwo_week_change": 41.48602426786651,
      "monthly_signal": null,
      "monthly_wt2": 45.794227894581354,
      "weekly_entry": null,
      "weekly_exit": null,
      "weekly_mfi": 13.811987869550345,
      "ash_bullish": false
    },
    {
      "ticker": "KWEB",
      "name": "China internet",
      "group": "Otros tem\u00e1ticos",
      "current_price": 23.940000534057617,
      "drawdown_from_ath_pct": -68.06559528091182,
      "fiftytwo_week_change": -28.33379925238264,
      "monthly_signal": null,
      "monthly_wt2": 7.956008190270129,
      "weekly_entry": null,
      "weekly_exit": null,
      "weekly_mfi": -9.681248514989553,
      "ash_bullish": false
    },
    {
      "ticker": "JETS",
      "name": "Aerol\u00edneas",
      "group": "Otros tem\u00e1ticos",
      "current_price": 33.279998779296875,
      "drawdown_from_ath_pct": 0.0,
      "fiftytwo_week_change": 40.0942906147935,
      "monthly_signal": null,
      "monthly_wt2": 50.35719278495632,
      "weekly_entry": null,
      "weekly_exit": null,
      "weekly_mfi": 13.351952218256336,
      "ash_bullish": false
    },
    {
      "ticker": "TLT",
      "name": "Bonos largos USA",
      "group": "Otros tem\u00e1ticos",
      "current_price": 87.36000061035156,
      "drawdown_from_ath_pct": -38.662500808873226,
      "fiftytwo_week_change": 5.090252459084098,
      "monthly_signal": null,
      "monthly_wt2": 3.4927010194583965,
      "weekly_entry": null,
      "weekly_exit": null,
      "weekly_mfi": 5.330380879540926,
      "ash_bullish": false
    }
  ]
}